yakumo/utils.py
yakumo/console.py
yakumo/constant.py
yakumo/__init__.py
yakumo/session.py
yakumo/patch.py
yakumo/base.py
yakumo/exception.py
yakumo/mapper.py
yakumo/smoketest.py
yakumo/cmd/__init__.py
yakumo/cmd/ossh.py
yakumo/cmd/run_tests.py
yakumo/cinder/__init__.py
yakumo/cinder/v1/__init__.py
yakumo/cinder/v1/snapshot.py
yakumo/cinder/v1/volume_type.py
yakumo/cinder/v1/volume.py
yakumo/cinder/v2/__init__.py
yakumo/cinder/v2/volume_backup.py
yakumo/cinder/v2/qos.py
yakumo/cinder/v2/quota_set.py
yakumo/cinder/v2/consistency_group_snapshot.py
yakumo/cinder/v2/snapshot.py
yakumo/cinder/v2/volume_type.py
yakumo/cinder/v2/consistency_group.py
yakumo/cinder/v2/volume.py
yakumo/cinder/v2/service.py
yakumo/cinder/v2/volume_transfer.py
yakumo/nova/__init__.py
yakumo/nova/v2/server.py
yakumo/nova/v2/key_pair.py
yakumo/nova/v2/hypervisor.py
yakumo/nova/v2/aggregate.py
yakumo/nova/v2/image.py
yakumo/nova/v2/__init__.py
yakumo/nova/v2/floating_ip.py
yakumo/nova/v2/availability_zone.py
yakumo/nova/v2/flavor.py
yakumo/nova/v2/quota_set.py
yakumo/nova/v2/agent.py
yakumo/nova/v2/floating_ip_dns.py
yakumo/nova/v2/interface_attachment.py
yakumo/nova/v2/volume_attachment.py
yakumo/nova/v2/certificate.py
yakumo/nova/v2/cloudpipe.py
yakumo/nova/v2/floating_ip_bulk.py
yakumo/nova/v2/security_group.py
yakumo/nova/v2/network.py
yakumo/nova/v2/server_group.py
yakumo/nova/v2/fixed_ip.py
yakumo/nova/v2/security_group_rule.py
yakumo/nova/v2/security_group_default_rule.py
yakumo/nova/v2/service.py
yakumo/keystone/__init__.py
yakumo/keystone/v3/credential.py
yakumo/keystone/v3/domain.py
yakumo/keystone/v3/__init__.py
yakumo/keystone/v3/group.py
yakumo/keystone/v3/region.py
yakumo/keystone/v3/project.py
yakumo/keystone/v3/service.py
yakumo/keystone/v3/role.py
yakumo/keystone/v3/endpoint.py
yakumo/keystone/v3/user.py
yakumo/keystone/v2/__init__.py
yakumo/keystone/v2/project.py
yakumo/keystone/v2/service.py
yakumo-0.11.0.dist-info/WHEEL
yakumo-0.11.0.dist-info/entry_points.txt
yakumo-0.11.0.dist-info/pbr.json
yakumo-0.11.0.dist-info/top_level.txt
yakumo-0.11.0.dist-info/RECORD
yakumo-0.11.0.dist-info/METADATA
yakumo-0.11.0.dist-info/DESCRIPTION.rst
yakumo-0.11.0.dist-info/metadata.json
