Metadata-Version: 2.0
Name: yakumo
Version: 0.11.0
Summary: Pythonic Unified OpenStack Client Library
Home-page: https://github.com/yosshy/python-yakumo
Author: Akira Yoshiyama
Author-email: akirayoshiyama@gmail.com
License: UNKNOWN
Platform: UNKNOWN
Classifier: Environment :: OpenStack
Classifier: Intended Audience :: Information Technology
Classifier: Intended Audience :: System Administrators
Classifier: License :: OSI Approved :: Apache Software License
Classifier: Operating System :: POSIX :: Linux
Classifier: Programming Language :: Python
Classifier: Programming Language :: Python :: 2
Classifier: Programming Language :: Python :: 2.7
Requires-Dist: os-client-config (>=1.13.0)
Requires-Dist: python-dateutil
Requires-Dist: simplejson
Requires-Dist: pbr
Requires-Dist: six
